bytoken
